zro2/__init__.py
zro2/easyocr.py
zro2/hashlib.py
zro2/io.py
zro2/json.py
zro2/keyring.py
zro2/logging.py
zro2/pandas.py
zro2/pygetwindow.py
zro2/pyscreeze.py
zro2/readchar.py
zro2/requests.py
zro2/screeninfo.py
zro2/subprocess.py
zro2/time.py
zro2/typing.py
zro2/uiautomator.py
zro2-0.2.0.dist-info/METADATA
zro2-0.2.0.dist-info/WHEEL
zro2-0.2.0.dist-info/RECORD
