Metadata-Version: 2.3
Name: zro2
Version: 0.2.0
Summary: util functions for projects
Author-email: ZackaryW <36378555+ZackaryW@users.noreply.github.com>
Requires-Python: >=3.8
Provides-Extra: extra
Requires-Dist: keyring>=25.1.0; extra == 'extra'
Requires-Dist: pygetwindow>=0.0.9; extra == 'extra'
Requires-Dist: pytest>=8.1.1; extra == 'extra'
Requires-Dist: readchar>=4.0.6; extra == 'extra'
Requires-Dist: screeninfo>=0.8.1; extra == 'extra'
